blueapi/__init__.py
blueapi/__main__.py
blueapi/_version.py
blueapi/config.py
blueapi/log.py
blueapi/cli/__init__.py
blueapi/cli/__main__.py
blueapi/cli/cli.py
blueapi/cli/format.py
blueapi/cli/scratch.py
blueapi/cli/updates.py
blueapi/client/__init__.py
blueapi/client/client.py
blueapi/client/event_bus.py
blueapi/client/numtracker.py
blueapi/client/rest.py
blueapi/core/__init__.py
blueapi/core/bluesky_event_loop.py
blueapi/core/bluesky_types.py
blueapi/core/context.py
blueapi/core/device_lookup.py
blueapi/core/event.py
blueapi/core/protocols.py
blueapi/service/__init__.py
blueapi/service/authentication.py
blueapi/service/interface.py
blueapi/service/main.py
blueapi/service/model.py
blueapi/service/openapi.py
blueapi/service/runner.py
blueapi/utils/__init__.py
blueapi/utils/base_model.py
blueapi/utils/connect_devices.py
blueapi/utils/file_permissions.py
blueapi/utils/invalid_config_error.py
blueapi/utils/modules.py
blueapi/utils/path_provider.py
blueapi/utils/serialization.py
blueapi/utils/thread_exception.py
blueapi/worker/__init__.py
blueapi/worker/event.py
blueapi/worker/task.py
blueapi/worker/task_worker.py
blueapi/worker/worker_errors.py
blueapi-2.dist-info/licenses/LICENSE
blueapi-2.dist-info/METADATA
blueapi-2.dist-info/WHEEL
blueapi-2.dist-info/entry_points.txt
blueapi-2.dist-info/top_level.txt
blueapi-2.dist-info/RECORD
