Metadata-Version: 2.4
Name: blueapi
Version: 2
Summary: Lightweight bluesky-as-a-service wrapper application. Also usable as a library.
Author-email: Callum Forrester <callum.forrester@diamond.ac.uk>
License:                                  Apache License
Project-URL: GitHub, https://github.com/DiamondLightSource/blueapi
Classifier: Development Status :: 3 - Alpha
Classifier: License :: OSI Approved :: Apache Software License
Classifier: Programming Language :: Python :: 3.11
Classifier: Programming Language :: Python :: 3.12
Classifier: Programming Language :: Python :: 3.13
Requires-Python: >=3.11
License-File: LICENSE
Requires-Dist: tiled[client]>=0.2.0
Requires-Dist: bluesky[plotting]>=1.14.0
Requires-Dist: ophyd-async>=0.13.5
Requires-Dist: aioca
Requires-Dist: pydantic>=2.0
Requires-Dist: scanspec>=0.9.0
Requires-Dist: pydantic-settings
Requires-Dist: stomp-py
Requires-Dist: PyYAML>=6.0.2
Requires-Dist: click>=8.2.0
Requires-Dist: fastapi>=0.112.0
Requires-Dist: uvicorn
Requires-Dist: requests
Requires-Dist: dls-dodal>=1.64.0
Requires-Dist: super-state-machine
Requires-Dist: GitPython
Requires-Dist: event-model==1.23.1
Requires-Dist: bluesky-stomp>=0.1.6
Requires-Dist: opentelemetry-distro>=0.48b0
Requires-Dist: opentelemetry-instrumentation-fastapi>=0.48b0
Requires-Dist: observability-utils>=0.1.4
Requires-Dist: pyjwt[crypto]
Requires-Dist: tomlkit
Requires-Dist: graypy>=2.1.0
Dynamic: license-file
